pyfastx.cp311-win_amd64.pyd
pyfastxcli.py
pyfastx-2.3.0.dist-info/licenses/LICENSE
pyfastx-2.3.0.dist-info/METADATA
pyfastx-2.3.0.dist-info/WHEEL
pyfastx-2.3.0.dist-info/entry_points.txt
pyfastx-2.3.0.dist-info/top_level.txt
pyfastx-2.3.0.dist-info/RECORD
